lidar_pbl/__init__.py
lidar_pbl/cli/app.py
lidar_pbl/core/__init__.py
lidar_pbl/core/lidar_dataset.py
lidar_pbl/core/methods.py
lidar_pbl/utils/__init__.py
lidar_pbl/utils/io.py
lidar_pbl/utils/misc.py
lidar_pbl/utils/rcs.py
lidar_pbl/utils/visualization.py
lidar_pbl-0.1.1.dist-info/entry_points.txt
lidar_pbl-0.1.1.dist-info/WHEEL
lidar_pbl-0.1.1.dist-info/METADATA
lidar_pbl-0.1.1.dist-info/RECORD
